mod77/__init__.py
mod77/a11.py
mod77/a22.py
pylibr-0.0.2.dist-info/LICENSE
pylibr-0.0.2.dist-info/METADATA
pylibr-0.0.2.dist-info/WHEEL
pylibr-0.0.2.dist-info/top_level.txt
pylibr-0.0.2.dist-info/RECORD
